{
  "activities": [

  ],
  "goals": {
    "activeMinutes": 30,
    "caloriesOut": 2123,
    "distance": 5,
    "steps": 10000
  },
  "summary": {
    "activeScore": -1,
    "activityCalories": 589,
    "caloriesBMR": 1214,
    "caloriesOut": 1683,
    "distances": [
      {
        "activity": "total",
        "distance": 2.81
      },
      {
        "activity": "tracker",
        "distance": 2.81
      },
      {
        "activity": "loggedActivities",
        "distance": 0
      },
      {
        "activity": "veryActive",
        "distance": 1.06
      },
      {
        "activity": "moderatelyActive",
        "distance": 0.18
      },
      {
        "activity": "lightlyActive",
        "distance": 1.57
      },
      {
        "activity": "sedentaryActive",
        "distance": 0
      }
    ],
    "fairlyActiveMinutes": 8,
    "lightlyActiveMinutes": 161,
    "marginalCalories": 295,
    "sedentaryMinutes": 645,
    "steps": 6851,
    "veryActiveMinutes": 24
  }
}