{"latitude":34.44833333333333,"longitude":-82.265,"timezone":"America/New_York","offset":-4,"currently":{"time":1377283200,"summary":"Clear","icon":"clear-day","precipIntensity":0,"precipProbability":0,"temperature":87.69,"apparentTemperature":92.17,"dewPoint":69.19,"humidity":0.54,"windSpeed":1.24,"windBearing":26,"visibility":9.44,"cloudCover":0.01,"pressure":1016.04},"hourly":{"summary":"Rain starting in the evening, continuing until night.","icon":"rain","data":[{"time":1377230400,"summary":"Clear","icon":"clear-night","precipIntensity":0,"precipProbability":0,"temperature":72.28,"apparentTemperature":72.28,"dewPoint":71.1,"humidity":0.96,"windSpeed":2.9,"windBearing":225,"visibility":8.76,"cloudCover":0,"pressure":1018},{"time":1377234000,"summary":"Clear","icon":"clear-night","precipIntensity":0,"precipProbability":0,"temperature":71.59,"apparentTemperature":71.59,"dewPoint":70.64,"humidity":0.97,"windSpeed":1.72,"windBearing":246,"visibility":8.59,"cloudCover":0,"pressure":1017.53},{"time":1377237600,"summary":"Clear","icon":"clear-night","precipIntensity":0,"precipProbability":0,"temperature":70.78,"apparentTemperature":70.78,"dewPoint":69.77,"humidity":0.97,"windSpeed":1.52,"windBearing":223,"visibility":7.09,"cloudCover":0,"pressure":1017.3},{"time":1377241200,"summary":"Clear","icon":"clear-night","precipIntensity":0,"precipProbability":0,"temperature":70.65,"apparentTemperature":70.65,"dewPoint":69.75,"humidity":0.97,"windSpeed":2.56,"windBearing":226,"visibility":6.15,"cloudCover":0,"pressure":1016.71},{"time":1377244800,"summary":"Clear","icon":"clear-night","precipIntensity":0,"precipProbability":0,"temperature":69.8,"apparentTemperature":69.8,"dewPoint":68.86,"humidity":0.97,"windSpeed":2.76,"windBearing":227,"visibility":5.75,"cloudCover":0,"pressure":1016.45},{"time":1377248400,"summary":"Clear","icon":"clear-night","precipIntensity":0,"precipProbability":0,"temperature":70.01,"apparentTemperature":70.01,"dewPoint":68.94,"humidity":0.96,"windSpeed":3.03,"windBearing":235,"visibility":4.69,"cloudCover":0,"pressure":1016.39},{"time":1377252000,"summary":"Clear","icon":"clear-night","precipIntensity":0,"precipProbability":0,"temperature":70.53,"apparentTemperature":70.53,"dewPoint":69.66,"humidity":0.97,"windSpeed":2.03,"windBearing":237,"visibility":3.32,"cloudCover":0,"pressure":1016.44},{"time":1377255600,"summary":"Clear","icon":"clear-night","precipIntensity":0,"precipProbability":0,"temperature":70.46,"apparentTemperature":70.46,"dewPoint":69.97,"humidity":0.98,"windSpeed":3.05,"windBearing":243,"visibility":3.3,"cloudCover":0,"pressure":1017.03},{"time":1377259200,"summary":"Clear","icon":"clear-day","precipIntensity":0,"precipProbability":0,"temperature":71.26,"apparentTemperature":71.26,"dewPoint":70.46,"humidity":0.97,"windSpeed":1.52,"windBearing":286,"visibility":5.86,"cloudCover":0.06,"pressure":1017.58},{"time":1377262800,"summary":"Clear","icon":"clear-day","precipIntensity":0,"precipProbability":0,"temperature":72.51,"apparentTemperature":72.51,"dewPoint":71.41,"humidity":0.96,"windSpeed":3,"windBearing":261,"visibility":7.51,"cloudCover":0,"pressure":1018.15},{"time":1377266400,"summary":"Clear","icon":"clear-day","precipIntensity":0,"precipProbability":0,"temperature":75.93,"apparentTemperature":75.93,"dewPoint":72.15,"humidity":0.88,"windSpeed":4.24,"windBearing":272,"visibility":9.53,"cloudCover":0,"pressure":1018.15},{"time":1377270000,"summary":"Clear","icon":"clear-day","precipIntensity":0,"precipProbability":0,"temperature":79.62,"apparentTemperature":79.62,"dewPoint":72.22,"humidity":0.78,"windSpeed":2.7,"windBearing":312,"visibility":10,"cloudCover":0,"pressure":1018.32},{"time":1377273600,"summary":"Clear","icon":"clear-day","precipIntensity":0,"precipProbability":0,"temperature":82.76,"apparentTemperature":87.97,"dewPoint":72.06,"humidity":0.7,"windSpeed":1.47,"windBearing":265,"visibility":10,"cloudCover":0,"pressure":1017.84},{"time":1377277200,"summary":"Clear","icon":"clear-day","precipIntensity":0,"precipProbability":0,"temperature":85.49,"apparentTemperature":90.38,"dewPoint":70.34,"humidity":0.61,"windSpeed":2.6,"windBearing":337,"visibility":9.82,"cloudCover":0,"pressure":1017.22},{"time":1377280800,"summary":"Clear","icon":"clear-day","precipIntensity":0,"precipProbability":0,"temperature":86.98,"apparentTemperature":91.78,"dewPoint":69.79,"humidity":0.57,"windSpeed":1.31,"windBearing":3,"visibility":9.38,"cloudCover":0.03,"pressure":1016.65},{"time":1377284400,"summary":"Clear","icon":"clear-day","precipIntensity":0,"precipProbability":0,"temperature":88.04,"apparentTemperature":92.35,"dewPoint":68.87,"humidity":0.53,"windSpeed":1.28,"windBearing":38,"visibility":9.47,"cloudCover":0,"pressure":1015.74},{"time":1377288000,"summary":"Clear","icon":"clear-day","precipIntensity":0,"precipProbability":0,"temperature":87.84,"apparentTemperature":92.21,"dewPoint":68.99,"humidity":0.54,"windSpeed":1.15,"windBearing":25,"visibility":9.82,"cloudCover":0,"pressure":1014.92},{"time":1377291600,"summary":"Clear","icon":"clear-day","precipIntensity":0,"precipProbability":0,"temperature":87.89,"apparentTemperature":92.69,"dewPoint":69.56,"humidity":0.55,"windSpeed":0.92,"windBearing":236,"visibility":9.64,"cloudCover":0.07,"pressure":1014.76},{"time":1377295200,"summary":"Rain","icon":"rain","precipIntensity":0.0886,"precipProbability":0.79,"precipType":"rain","temperature":84.08,"apparentTemperature":88.64,"dewPoint":70.34,"humidity":0.64,"windSpeed":4.59,"windBearing":44,"visibility":9.61,"cloudCover":0,"pressure":1015.55},{"time":1377298800,"summary":"Rain","icon":"rain","precipIntensity":0.0765,"precipProbability":0.77,"precipType":"rain","temperature":79.33,"apparentTemperature":79.33,"dewPoint":71.64,"humidity":0.77,"windSpeed":4.26,"windBearing":10,"visibility":9.35,"cloudCover":0,"pressure":1015.74},{"time":1377302400,"summary":"Light Rain","icon":"rain","precipIntensity":0.0226,"precipProbability":0.62,"precipType":"rain","temperature":74.99,"apparentTemperature":74.99,"dewPoint":71.65,"humidity":0.89,"windSpeed":1.67,"windBearing":223,"visibility":8.74,"cloudCover":0.05,"pressure":1016.63},{"time":1377306000,"summary":"Light Rain","icon":"rain","precipIntensity":0.0244,"precipProbability":0.63,"precipType":"rain","temperature":73.26,"apparentTemperature":73.26,"dewPoint":70.4,"humidity":0.91,"windSpeed":1.2,"windBearing":305,"visibility":8.81,"cloudCover":0,"pressure":1017.32},{"time":1377309600,"summary":"Drizzle","icon":"rain","precipIntensity":0.0076,"precipProbability":0.38,"precipType":"rain","temperature":72.53,"apparentTemperature":72.53,"dewPoint":70.53,"humidity":0.93,"windSpeed":1.64,"windBearing":304,"visibility":9.26,"cloudCover":0,"pressure":1017.26},{"time":1377313200,"summary":"Clear","icon":"clear-night","precipIntensity":0,"precipProbability":0,"temperature":71.99,"apparentTemperature":71.99,"dewPoint":69.88,"humidity":0.93,"windSpeed":2.2,"windBearing":325,"visibility":8.83,"cloudCover":0,"pressure":1017.3}]},"daily":{"data":[{"time":1377230400,"summary":"Rain starting in the evening.","icon":"rain","sunriseTime":1377255447,"sunsetTime":1377302925,"moonPhase":0.6,"precipIntensity":0.0092,"precipIntensityMax":0.0886,"precipIntensityMaxTime":1377295200,"precipProbability":0.79,"precipType":"rain","temperatureMin":69.8,"temperatureMinTime":1377244800,"temperatureMax":88.04,"temperatureMaxTime":1377284400,"apparentTemperatureMin":69.8,"apparentTemperatureMinTime":1377244800,"apparentTemperatureMax":92.35,"apparentTemperatureMaxTime":1377284400,"dewPoint":70.37,"humidity":0.83,"windSpeed":1.22,"windBearing":280,"visibility":8.05,"cloudCover":0.01,"pressure":1016.87}]},"flags":{"sources":["isd"],"isd-stations":["720294-53898","720596-00189","720596-99999","720597-99999","720601-99999","720744-00271","723118-53850","723119-13886","723120-03870","723122-63889","723124-53874","723126-99999","723190-93846","725258-99999","998177-99999","998205-99999"],"units":"us"}}