{"latitude":36.888333333333335,"longitude":-87.49166666666666,"timezone":"America/Chicago","offset":-5,"currently":{"time":1440181560,"summary":"Clear","icon":"clear-day","precipIntensity":0,"precipProbability":0,"temperature":79.22,"apparentTemperature":79.22,"dewPoint":56.76,"humidity":0.46,"windSpeed":6.96,"windBearing":94,"visibility":10,"cloudCover":0.1,"pressure":1019.75},"hourly":{"summary":"Clear throughout the day.","icon":"clear-day","data":[{"time":1440133200,"summary":"Clear","icon":"clear-night","precipIntensity":0,"precipProbability":0,"temperature":61.77,"apparentTemperature":61.77,"dewPoint":58.42,"humidity":0.89,"windSpeed":0,"visibility":9.87,"cloudCover":0,"pressure":1018.43},{"time":1440136800,"summary":"Clear","icon":"clear-night","precipIntensity":0,"precipProbability":0,"temperature":59.91,"apparentTemperature":59.91,"dewPoint":57.74,"humidity":0.93,"windSpeed":3,"windBearing":30,"visibility":10,"cloudCover":0.02,"pressure":1018.34},{"time":1440140400,"summary":"Clear","icon":"clear-night","precipIntensity":0,"precipProbability":0,"temperature":59.5,"apparentTemperature":59.5,"dewPoint":57.66,"humidity":0.94,"windSpeed":2.99,"windBearing":18,"visibility":9.09,"cloudCover":0.01,"pressure":1018.23},{"time":1440144000,"summary":"Clear","icon":"clear-night","precipIntensity":0,"precipProbability":0,"temperature":58.67,"apparentTemperature":58.67,"dewPoint":57.01,"humidity":0.94,"windSpeed":0,"visibility":8.59,"cloudCover":0,"pressure":1018.4},{"time":1440147600,"summary":"Clear","icon":"clear-night","precipIntensity":0,"precipProbability":0,"temperature":57.65,"apparentTemperature":57.65,"dewPoint":56.37,"humidity":0.95,"windSpeed":0,"visibility":6.88,"cloudCover":0,"pressure":1018.41},{"time":1440151200,"summary":"Clear","icon":"clear-night","precipIntensity":0,"precipProbability":0,"temperature":56.47,"apparentTemperature":56.47,"dewPoint":55.62,"humidity":0.97,"windSpeed":3,"windBearing":20,"visibility":6.13,"cloudCover":0,"pressure":1018.5},{"time":1440154800,"summary":"Clear","icon":"clear-night","precipIntensity":0,"precipProbability":0,"temperature":56.49,"apparentTemperature":56.49,"dewPoint":55.56,"humidity":0.97,"windSpeed":1,"windBearing":80,"visibility":5.74,"cloudCover":0.02,"pressure":1018.91},{"time":1440158400,"summary":"Clear","icon":"clear-day","precipIntensity":0,"precipProbability":0,"temperature":59.4,"apparentTemperature":59.4,"dewPoint":57.42,"humidity":0.93,"windSpeed":0,"visibility":7.77,"cloudCover":0.03,"pressure":1019.58},{"time":1440162000,"summary":"Clear","icon":"clear-day","precipIntensity":0,"precipProbability":0,"temperature":64.55,"apparentTemperature":64.55,"dewPoint":61.13,"humidity":0.89,"windSpeed":2.75,"windBearing":60,"visibility":9.66,"cloudCover":0.02,"pressure":1020.11},{"time":1440165600,"summary":"Clear","icon":"clear-day","precipIntensity":0,"precipProbability":0,"temperature":69.5,"apparentTemperature":69.5,"dewPoint":61.37,"humidity":0.75,"windSpeed":3.42,"windBearing":96,"visibility":10,"cloudCover":0.02,"pressure":1020.52},{"time":1440169200,"summary":"Clear","icon":"clear-day","precipIntensity":0,"precipProbability":0,"temperature":74.63,"apparentTemperature":74.63,"dewPoint":59.73,"humidity":0.6,"windSpeed":6.06,"windBearing":93,"visibility":10,"cloudCover":0.11,"pressure":1020.55},{"time":1440172800,"summary":"Clear","icon":"clear-day","precipIntensity":0,"precipProbability":0,"temperature":76.21,"apparentTemperature":76.21,"dewPoint":60.85,"humidity":0.59,"windSpeed":6.94,"windBearing":99,"visibility":10,"cloudCover":0.08,"pressure":1020.87},{"time":1440176400,"summary":"Clear","icon":"clear-day","precipIntensity":0,"precipProbability":0,"temperature":77.63,"apparentTemperature":77.63,"dewPoint":56.21,"humidity":0.48,"windSpeed":6.44,"windBearing":87,"visibility":10,"cloudCover":0.04,"pressure":1020.52},{"time":1440180000,"summary":"Clear","icon":"clear-day","precipIntensity":0,"precipProbability":0,"temperature":79,"apparentTemperature":79,"dewPoint":56.67,"humidity":0.46,"windSpeed":7.4,"windBearing":84,"visibility":10,"cloudCover":0.15,"pressure":1019.93},{"time":1440183600,"summary":"Clear","icon":"clear-day","precipIntensity":0,"precipProbability":0,"temperature":79.51,"apparentTemperature":79.51,"dewPoint":56.87,"humidity":0.46,"windSpeed":6.68,"windBearing":107,"visibility":10,"cloudCover":0.03,"pressure":1019.52},{"time":1440187200,"summary":"Clear","icon":"clear-day","precipIntensity":0,"precipProbability":0,"temperature":80.47,"apparentTemperature":80.55,"dewPoint":56.06,"humidity":0.43,"windSpeed":4.95,"windBearing":98,"visibility":10,"cloudCover":0.03,"pressure":1019.03},{"time":1440190800,"summary":"Clear","icon":"clear-day","precipIntensity":0,"precipProbability":0,"temperature":80.95,"apparentTemperature":80.93,"dewPoint":56.48,"humidity":0.43,"windSpeed":3.58,"windBearing":88,"visibility":10,"cloudCover":0.07,"pressure":1018.49},{"time":1440194400,"summary":"Clear","icon":"clear-day","precipIntensity":0,"precipProbability":0,"temperature":80.45,"apparentTemperature":80.67,"dewPoint":56.89,"humidity":0.45,"windSpeed":4.6,"windBearing":91,"visibility":10,"cloudCover":0.03,"pressure":1018.11},{"time":1440198000,"summary":"Clear","icon":"clear-day","precipIntensity":0,"precipProbability":0,"temperature":79.67,"apparentTemperature":79.67,"dewPoint":57.02,"humidity":0.46,"windSpeed":3.77,"windBearing":74,"visibility":10,"cloudCover":0.03,"pressure":1018.05},{"time":1440201600,"summary":"Clear","icon":"clear-day","precipIntensity":0,"precipProbability":0,"temperature":75.33,"apparentTemperature":75.33,"dewPoint":60.31,"humidity":0.6,"windSpeed":2.96,"windBearing":70,"visibility":10,"cloudCover":0.03,"pressure":1017.92},{"time":1440205200,"summary":"Clear","icon":"clear-night","precipIntensity":0,"precipProbability":0,"temperature":70.23,"apparentTemperature":70.23,"dewPoint":61.18,"humidity":0.73,"windSpeed":2.24,"windBearing":45,"visibility":10,"cloudCover":0.02,"pressure":1018.1},{"time":1440208800,"summary":"Clear","icon":"clear-night","precipIntensity":0,"precipProbability":0,"temperature":67.45,"apparentTemperature":67.45,"dewPoint":61.41,"humidity":0.81,"windSpeed":1.89,"windBearing":50,"visibility":10,"cloudCover":0.02,"pressure":1018.66},{"time":1440212400,"summary":"Clear","icon":"clear-night","precipIntensity":0,"precipProbability":0,"temperature":65.92,"apparentTemperature":65.92,"dewPoint":61.32,"humidity":0.85,"windSpeed":1.67,"windBearing":71,"visibility":9.87,"cloudCover":0.02,"pressure":1018.94},{"time":1440216000,"summary":"Clear","icon":"clear-night","precipIntensity":0,"precipProbability":0,"temperature":64.23,"apparentTemperature":64.23,"dewPoint":61.03,"humidity":0.89,"windSpeed":3.13,"windBearing":71,"visibility":8.91,"cloudCover":0.02,"pressure":1018.52}]},"daily":{"data":[{"time":1440133200,"summary":"Clear throughout the day.","icon":"clear-day","sunriseTime":1440155590,"sunsetTime":1440203766,"moonPhase":0.22,"precipIntensity":0,"precipIntensityMax":0,"precipProbability":0,"temperatureMin":56.47,"temperatureMinTime":1440151200,"temperatureMax":80.95,"temperatureMaxTime":1440190800,"apparentTemperatureMin":56.47,"apparentTemperatureMinTime":1440151200,"apparentTemperatureMax":80.93,"apparentTemperatureMaxTime":1440190800,"dewPoint":58.35,"humidity":0.72,"windSpeed":2.98,"windBearing":80,"visibility":9.27,"cloudCover":0.03,"pressure":1019.03}]},"flags":{"sources":["isd"],"isd-stations":["720170-63851","720447-00437","720447-99999","722322-99999","722781-99999","723270-13897","723273-13827","723280-03894","724237-53803","724238-53886","724320-93817","724350-03816","746710-13806","746716-93808","999999-00421","999999-63849"],"units":"us"}}