{"latitude":42.80833333333333,"longitude":-106.25666666666666,"timezone":"America/Denver","offset":-6,"currently":{"time":1345743840,"summary":"Clear","icon":"clear-day","precipIntensity":0,"precipProbability":0,"temperature":80.22,"apparentTemperature":79.21,"dewPoint":44.47,"humidity":0.28,"windSpeed":7.11,"windBearing":192,"visibility":10,"cloudCover":0.01,"pressure":1009.59},"hourly":{"summary":"Clear throughout the day.","icon":"clear-day","data":[{"time":1345701600,"summary":"Clear","icon":"clear-night","precipIntensity":0.0011,"precipProbability":0.01,"precipType":"rain","temperature":67.77,"apparentTemperature":67.77,"dewPoint":44.74,"humidity":0.43,"windSpeed":5.39,"windBearing":203,"visibility":9.63,"cloudCover":0.12,"pressure":1009.74},{"time":1345705200,"summary":"Clear","icon":"clear-night","precipIntensity":0,"precipProbability":0,"temperature":67.93,"apparentTemperature":67.93,"dewPoint":43.59,"humidity":0.41,"windSpeed":5.63,"windBearing":224,"visibility":10,"cloudCover":0.19,"pressure":1009.81},{"time":1345708800,"summary":"Clear","icon":"clear-night","precipIntensity":0,"precipProbability":0,"temperature":65.38,"apparentTemperature":65.38,"dewPoint":44.35,"humidity":0.47,"windSpeed":2.39,"windBearing":158,"visibility":10,"cloudCover":0.1,"pressure":1009.91},{"time":1345712400,"summary":"Clear","icon":"clear-night","precipIntensity":0,"precipProbability":0,"temperature":64.91,"apparentTemperature":64.91,"dewPoint":44.45,"humidity":0.47,"windSpeed":8.49,"windBearing":212,"visibility":10,"cloudCover":0.05,"pressure":1009.86},{"time":1345716000,"summary":"Partly Cloudy","icon":"partly-cloudy-night","precipIntensity":0,"precipProbability":0,"temperature":62.63,"apparentTemperature":62.63,"dewPoint":44.92,"humidity":0.52,"windSpeed":3.55,"windBearing":217,"visibility":10,"cloudCover":0.44,"pressure":1009.97},{"time":1345719600,"summary":"Clear","icon":"clear-night","precipIntensity":0,"precipProbability":0,"temperature":60.33,"apparentTemperature":60.33,"dewPoint":43.72,"humidity":0.54,"windSpeed":2.81,"windBearing":175,"visibility":10,"cloudCover":0.09,"pressure":1010.25},{"time":1345723200,"summary":"Clear","icon":"clear-night","precipIntensity":0,"precipProbability":0,"temperature":58.79,"apparentTemperature":58.79,"dewPoint":43.78,"humidity":0.57,"windSpeed":3.64,"windBearing":229,"visibility":10,"cloudCover":0.08,"pressure":1010.54},{"time":1345726800,"summary":"Clear","icon":"clear-day","precipIntensity":0,"precipProbability":0,"temperature":58.49,"apparentTemperature":58.49,"dewPoint":43.24,"humidity":0.57,"windSpeed":5.86,"windBearing":252,"visibility":10,"cloudCover":0.05,"pressure":1011},{"time":1345730400,"summary":"Clear","icon":"clear-day","precipIntensity":0,"precipProbability":0,"temperature":62.13,"apparentTemperature":62.13,"dewPoint":45.01,"humidity":0.53,"windSpeed":1.27,"windBearing":194,"visibility":10,"cloudCover":0.02,"pressure":1011.58},{"time":1345734000,"summary":"Clear","icon":"clear-day","precipIntensity":0,"precipProbability":0,"temperature":68.67,"apparentTemperature":68.67,"dewPoint":45.01,"humidity":0.43,"windSpeed":5.85,"windBearing":154,"visibility":9.91,"cloudCover":0.15,"pressure":1011.33},{"time":1345737600,"summary":"Clear","icon":"clear-day","precipIntensity":0,"precipProbability":0,"temperature":74.39,"apparentTemperature":74.39,"dewPoint":45.97,"humidity":0.36,"windSpeed":4.05,"windBearing":158,"visibility":10,"cloudCover":0.16,"pressure":1010.84},{"time":1345741200,"summary":"Clear","icon":"clear-day","precipIntensity":0,"precipProbability":0,"temperature":77.72,"apparentTemperature":77.72,"dewPoint":45.16,"humidity":0.32,"windSpeed":7.59,"windBearing":223,"visibility":10,"cloudCover":0,"pressure":1010.14},{"time":1345744800,"summary":"Clear","icon":"clear-day","precipIntensity":0,"precipProbability":0,"temperature":81.13,"apparentTemperature":79.7,"dewPoint":44.13,"humidity":0.27,"windSpeed":7.45,"windBearing":181,"visibility":10,"cloudCover":0.02,"pressure":1009.39},{"time":1345748400,"summary":"Clear","icon":"clear-day","precipIntensity":0,"precipProbability":0,"temperature":82.97,"apparentTemperature":80.7,"dewPoint":41.62,"humidity":0.23,"windSpeed":5.96,"windBearing":203,"visibility":10,"cloudCover":0.03,"pressure":1008.29},{"time":1345752000,"summary":"Clear","icon":"clear-day","precipIntensity":0,"precipProbability":0,"temperature":85.64,"apparentTemperature":82.57,"dewPoint":40.72,"humidity":0.21,"windSpeed":6.72,"windBearing":196,"visibility":10,"cloudCover":0.05,"pressure":1007.53},{"time":1345755600,"summary":"Clear","icon":"clear-day","precipIntensity":0,"precipProbability":0,"temperature":86.29,"apparentTemperature":83.04,"dewPoint":39.71,"humidity":0.19,"windSpeed":6.75,"windBearing":161,"visibility":10,"cloudCover":0.09,"pressure":1006.74},{"time":1345759200,"summary":"Clear","icon":"clear-day","precipIntensity":0,"precipProbability":0,"temperature":85.91,"apparentTemperature":82.7,"dewPoint":38.57,"humidity":0.19,"windSpeed":10.83,"windBearing":160,"visibility":10,"cloudCover":0.15,"pressure":1006.44},{"time":1345762800,"summary":"Partly Cloudy","icon":"partly-cloudy-day","precipIntensity":0,"precipProbability":0,"temperature":86.85,"apparentTemperature":83.4,"dewPoint":37.36,"humidity":0.17,"windSpeed":9.48,"windBearing":145,"visibility":10,"cloudCover":0.36,"pressure":1005.81},{"time":1345766400,"summary":"Clear","icon":"clear-day","precipIntensity":0,"precipProbability":0,"temperature":84.83,"apparentTemperature":81.82,"dewPoint":36.79,"humidity":0.18,"windSpeed":6.96,"windBearing":161,"visibility":10,"cloudCover":0.02,"pressure":1005.85},{"time":1345770000,"summary":"Clear","icon":"clear-day","precipIntensity":0,"precipProbability":0,"temperature":83.15,"apparentTemperature":80.64,"dewPoint":37.49,"humidity":0.2,"windSpeed":7.91,"windBearing":152,"visibility":10,"cloudCover":0,"pressure":1005.51},{"time":1345773600,"summary":"Clear","icon":"clear-night","precipIntensity":0,"precipProbability":0,"temperature":77.9,"apparentTemperature":77.9,"dewPoint":33.34,"humidity":0.2,"windSpeed":4.57,"windBearing":162,"visibility":10,"cloudCover":0,"pressure":1005.62},{"time":1345777200,"summary":"Clear","icon":"clear-night","precipIntensity":0,"precipProbability":0,"temperature":71.99,"apparentTemperature":71.99,"dewPoint":33.44,"humidity":0.24,"windSpeed":1.72,"windBearing":109,"visibility":9.71,"cloudCover":0,"pressure":1006.05},{"time":1345780800,"summary":"Clear","icon":"clear-night","precipIntensity":0,"precipProbability":0,"temperature":69.91,"apparentTemperature":69.91,"dewPoint":33.57,"humidity":0.26,"windSpeed":4.87,"windBearing":203,"visibility":9.96,"cloudCover":0,"pressure":1006.01},{"time":1345784400,"summary":"Clear","icon":"clear-night","precipIntensity":0,"precipProbability":0,"temperature":68.25,"apparentTemperature":68.25,"dewPoint":37.03,"humidity":0.32,"windSpeed":6.02,"windBearing":212,"visibility":10,"cloudCover":0,"pressure":1005.73}]},"daily":{"data":[{"time":1345701600,"summary":"Clear throughout the day.","icon":"clear-day","sunriseTime":1345724524,"sunsetTime":1345773354,"moonPhase":0.22,"precipIntensity":0.0001,"precipIntensityMax":0.0011,"precipIntensityMaxTime":1345701600,"precipProbability":0.01,"precipType":"rain","temperatureMin":58.49,"temperatureMinTime":1345726800,"temperatureMax":86.85,"temperatureMaxTime":1345762800,"apparentTemperatureMin":58.49,"apparentTemperatureMinTime":1345726800,"apparentTemperatureMax":83.4,"apparentTemperatureMaxTime":1345762800,"dewPoint":41.15,"humidity":0.35,"windSpeed":4.85,"windBearing":185,"visibility":9.97,"cloudCover":0.09,"pressure":1008.5}]},"flags":{"sources":["isd"],"isd-stations":["720747-99999","720969-99999","721036-99999","725645-24022","725686-94057","725690-24089","725763-94053","726650-94023","726654-94054","726665-24062","726690-24057","726720-24061","999999-94078"],"units":"us"}}